LICENSE
README.md
setup.py
reaccess/__init__.py
reaccess/__main__.py
reaccess/client.py
reaccess/server.py
reaccess.egg-info/PKG-INFO
reaccess.egg-info/SOURCES.txt
reaccess.egg-info/dependency_links.txt
reaccess.egg-info/entry_points.txt
reaccess.egg-info/requires.txt
reaccess.egg-info/top_level.txt