Metadata-Version: 2.1
Name: reaccess
Version: 0.1.0
Summary: Execute commands on another machine remotely.
Home-page: https://github.com/jaedsonpys/REaccess
Author: Jaedson Silva
Author-email: imunknowuser@protonmail.com
License: Apache 2.0
Keywords: remote,backdoor,access
License-File: LICENSE
